album_splitter/__init__.py
album_splitter/__main__.py
album_splitter/parse_tracks.py
album_splitter/split_file.py
album_splitter/tag_file.py
album_splitter/tests/__init__.py
album_splitter/tests/test_parse_tracks.py
album_splitter/utils/__init__.py
album_splitter/utils/secure_filename.py
album_splitter/utils/ytdl_interface.py
album_splitter-1.0.2.dist-info/LICENSE
album_splitter-1.0.2.dist-info/METADATA
album_splitter-1.0.2.dist-info/WHEEL
album_splitter-1.0.2.dist-info/entry_points.txt
album_splitter-1.0.2.dist-info/top_level.txt
album_splitter-1.0.2.dist-info/RECORD
