Metadata-Version: 2.2
Name: album-splitter
Version: 1.0.2
Summary: Split single-file MP3 albums into separate tracks. Download from YouTube supported.
Author-email: Cristian Baldi <bld.cris.96@gmail.com>
Project-URL: Homepage, https://github.com/crisbal/album-splitter/
Project-URL: Documentation, https://github.com/crisbal/album-splitter/README.md
Project-URL: Repository, https://github.com/crisbal/album-splitter/
Project-URL: Tracker, https://github.com/crisbal/album-splitter/issues
Classifier: Programming Language :: Python :: 3
Classifier: Operating System :: OS Independent
Classifier: License :: OSI Approved :: GNU General Public License v3 (GPLv3)
Classifier: Topic :: Multimedia :: Sound/Audio
Requires-Python: >=3.12
License-File: LICENSE
Requires-Dist: ffmpy
Requires-Dist: music_tag
Requires-Dist: yt-dlp
Provides-Extra: test
Requires-Dist: pytest; extra == "test"
